analytics_mcp/__init__.py
analytics_mcp/coordinator.py
analytics_mcp/server.py
analytics_mcp/tools/__init__.py
analytics_mcp/tools/utils.py
analytics_mcp/tools/admin/info.py
analytics_mcp/tools/reporting/__init__.py
analytics_mcp/tools/reporting/core.py
analytics_mcp/tools/reporting/metadata.py
analytics_mcp/tools/reporting/realtime.py
analytics_mcp-0.1.0.dist-info/licenses/LICENSE
analytics_mcp-0.1.0.dist-info/METADATA
analytics_mcp-0.1.0.dist-info/WHEEL
analytics_mcp-0.1.0.dist-info/entry_points.txt
analytics_mcp-0.1.0.dist-info/top_level.txt
analytics_mcp-0.1.0.dist-info/RECORD
