Metadata-Version: 2.4
Name: analytics-mcp
Version: 0.1.0
License-Expression: Apache-2.0
Requires-Python: <3.14,>=3.10
License-File: LICENSE
Requires-Dist: google-analytics-data==0.18.19
Requires-Dist: google-analytics-admin==0.24.1
Requires-Dist: google-auth~=2.40
Requires-Dist: mcp[cli]>=1.2.0
Requires-Dist: httpx>=0.28.1
Provides-Extra: dev
Requires-Dist: black; extra == "dev"
Requires-Dist: nox<2026,>=2025.5.1; extra == "dev"
Dynamic: license-file
